ex_motor-0.5.dist-info/DESCRIPTION.rst
ex_motor-0.5.dist-info/METADATA
ex_motor-0.5.dist-info/RECORD
ex_motor-0.5.dist-info/WHEEL
ex_motor-0.5.dist-info/metadata.json
ex_motor-0.5.dist-info/top_level.txt
motor/__init__.py
motor/core.py
motor/metaprogramming.py
motor/motor_asyncio.py
motor/motor_common.py
motor/motor_gridfs.py
motor/motor_py3_compat.py
motor/motor_tornado.py
motor/util.py
motor/web.py
motor/frameworks/__init__.py
motor/frameworks/asyncio.py
motor/frameworks/tornado.py
