Metadata-Version: 2.0
Name: ex-motor
Version: 0.5
Summary: Non-blocking MongoDB driver for Tornado or asyncio
Home-page: UNKNOWN
Author: i.tolkachnikov
Author-email: i.tolkachnikov@gmail.com
License: http://www.apache.org/licenses/LICENSE-2.0
Keywords: mongo,mongodb,pymongo,gridfs,bson,motor,tornado,asyncio
Platform: UNKNOWN
Classifier: Intended Audience :: Developers
Classifier: License :: OSI Approved :: Apache Software License
Classifier: Development Status :: 4 - Beta
Classifier: Natural Language :: English
Classifier: Programming Language :: Python :: 2
Classifier: Programming Language :: Python :: 2.6
Classifier: Programming Language :: Python :: 2.7
Classifier: Programming Language :: Python :: 3
Classifier: Programming Language :: Python :: 3.3
Classifier: Programming Language :: Python :: 3.4
Classifier: Programming Language :: Python :: 3.5
Classifier: Operating System :: MacOS :: MacOS X
Classifier: Operating System :: Unix
Classifier: Programming Language :: Python
Classifier: Programming Language :: Python :: Implementation :: CPython
Requires-Dist: greenlet (>=0.4.0)
Requires-Dist: pymongo (==2.8.0)
